corrpy/__init__.py
corrpy/core.py
corrpy-0.4.11.dist-info/METADATA
corrpy-0.4.11.dist-info/WHEEL
corrpy-0.4.11.dist-info/top_level.txt
corrpy-0.4.11.dist-info/RECORD
