Metadata-Version: 2.4
Name: Corrpy
Version: 0.4.11
Summary: Correlation analysis tool with smart interpretation
Author: YellowForest
License: BSD-3-Clause
Project-URL: Homepage, https://github.com/Parthdsaiml/corrpy
Requires-Python: >=3.7
Requires-Dist: pandas
Requires-Dist: numpy
Requires-Dist: scipy
Requires-Dist: matplotlib
Requires-Dist: seaborn
Requires-Dist: IPython
Requires-Dist: together
Requires-Dist: scikit-learn
